pika/__init__.py
pika/gripper.py
pika/sense.py
pika/serial_comm.py
pika/camera/__init__.py
pika/camera/fisheye.py
pika/camera/realsense.py
pika/tracker/__init__.py
pika/tracker/pose_utils.py
pika/tracker/vive_tracker.py
agx_pypika-0.1.0.dist-info/METADATA
agx_pypika-0.1.0.dist-info/WHEEL
agx_pypika-0.1.0.dist-info/top_level.txt
agx_pypika-0.1.0.dist-info/RECORD
