Metadata-Version: 2.1
Name: agx-pypika
Version: 0.1.0
Summary: Pika SDK for robotics applications
Home-page: https://github.com/agilexrobotics/pika_sdk
Author: Agilex Robotics RoboPPN
Author-email: support@agilex.ai
Keywords: robotics,sdk,pika,data
Platform: Linux
Classifier: Intended Audience :: Developers
Classifier: License :: OSI Approved :: MIT License
Classifier: Operating System :: OS Independent
Classifier: Programming Language :: Python
Classifier: Programming Language :: Python :: 3
Classifier: Programming Language :: Python :: 3.6
Classifier: Programming Language :: Python :: 3.7
Classifier: Programming Language :: Python :: 3.8
Classifier: Programming Language :: Python :: 3.9
Classifier: Programming Language :: Python :: 3.10
Classifier: Programming Language :: Python :: 3.11
Classifier: Programming Language :: Python :: 3.12
Classifier: Programming Language :: Python :: 3.13
Classifier: Topic :: Software Development
Requires-Python: >=3.6
Requires-Dist: numpy
Requires-Dist: opencv-python
Requires-Dist: pyserial
Requires-Dist: pyrealsense2
Requires-Dist: pysurvive
Requires-Dist: wxpython
Requires-Dist: Gooey
